mensajes/__init__.py
mensajes/adios/__init__.py
mensajes/adios/despedidas.py
mensajes/hola/__init__.py
mensajes/hola/saludos.py
tests/__init__.py
tests/test_hola.py
Mensajes_angelus-1.6.dist-info/LICENSE
Mensajes_angelus-1.6.dist-info/METADATA
Mensajes_angelus-1.6.dist-info/WHEEL
Mensajes_angelus-1.6.dist-info/top_level.txt
Mensajes_angelus-1.6.dist-info/RECORD
