Metadata-Version: 2.1
Name: Mensajes-angelus
Version: 1.6
Summary: Paquete para saludar y despedir
Home-page: https://github.com/angelus
Author: angelus
Author-email: cloud.angelus@gmail.com
Classifier: Environment :: Console
Classifier: Topic :: Utilities
License-File: LICENSE
Requires-Dist: numpy (>=1.25.1)
